CTkColorPicker/__init__.py
CTkColorPicker/color_wheel.png
CTkColorPicker/ctk_color_picker.py
CTkColorPicker/ctk_color_picker_widget.py
CTkColorPicker/target.png
CTkColorPicker-0.9.0.dist-info/LICENSE
CTkColorPicker-0.9.0.dist-info/METADATA
CTkColorPicker-0.9.0.dist-info/WHEEL
CTkColorPicker-0.9.0.dist-info/dependency_links.txt
CTkColorPicker-0.9.0.dist-info/top_level.txt
CTkColorPicker-0.9.0.dist-info/RECORD
