Metadata-Version: 2.1
Name: CTkColorPicker
Version: 0.9.0
Summary: A modern color picker for customtkinter
Home-page: https://github.com/Akascape/CTkColorPicker
Author: Akash Bora
License: Creative Commons Zero v1.0 Universal
Keywords: customtkinter,customtkinter-dialog,customtkinter-color-picker,customtkinter-colour-picker,customtkinter-color,customtkinter-color-chooser,color-picker,python-color-picker
Classifier: License :: CC0 1.0 Universal (CC0 1.0) Public Domain Dedication
Classifier: Programming Language :: Python :: 3
Classifier: Operating System :: OS Independent
Requires-Python: >=3.6
License-File: LICENSE
Requires-Dist: customtkinter
Requires-Dist: pillow
